pytoc/__init__.py
pytoc/context.py
pytoc/enums.py
pytoc/file_entry.py
pytoc/meta.py
pytoc/py.typed
pytoc/toc.py
wow_pytoc-0.7.0.dist-info/WHEEL
wow_pytoc-0.7.0.dist-info/METADATA
wow_pytoc-0.7.0.dist-info/RECORD
