Metadata-Version: 2.3
Name: wow-pytoc
Version: 0.7.0
Summary: A package for reading and writing World of Warcraft addon TOC files.
Author: Ghostopheles
Author-email: Ghostopheles <ghost@ghst.tools>
License: This is free and unencumbered software released into the public domain.
Classifier: Development Status :: 4 - Beta
Classifier: Intended Audience :: Developers
Classifier: License :: Public Domain
Classifier: Programming Language :: Python :: 3
Classifier: Programming Language :: Python :: 3 :: Only
Requires-Python: >=3.12
Project-URL: Changelog, https://github.com/Ghostopheles/pytoc/blob/master/CHANGELOG.md
Project-URL: Homepage, https://github.com/Ghostopheles/pytoc
Project-URL: Issues, https://github.com/Ghostopheles/pytoc/issues
Project-URL: Repository, https://github.com/Ghostopheles/pytoc.git
